PythonPackageUpdateChecker/__init__.py
PythonPackageUpdateChecker/__main__.py
PythonPackageUpdateChecker-1.0.15.dist-info/LICENSE.txt
PythonPackageUpdateChecker-1.0.15.dist-info/METADATA
PythonPackageUpdateChecker-1.0.15.dist-info/WHEEL
PythonPackageUpdateChecker-1.0.15.dist-info/entry_points.txt
PythonPackageUpdateChecker-1.0.15.dist-info/top_level.txt
PythonPackageUpdateChecker-1.0.15.dist-info/RECORD
