Metadata-Version: 2.1
Name: PythonPackageUpdateChecker
Version: 1.0.15
Summary: A utility to automatically check for updates of installed Python packages and update them to the latest versions.
Author: Andrii Bohachev
Author-email: andriybogachev@gmail.com
License: MIT
Project-URL: Source, https://github.com/andriybogachev/PythonPackageUpdateChecker
Project-URL: Bug Reports, https://github.com/andriybogachev/PythonPackageUpdateChecker/issues
Keywords: python package update checker utility async aiohttp
Classifier: Development Status :: 5 - Production/Stable
Classifier: Intended Audience :: Developers
Classifier: License :: OSI Approved :: MIT License
Classifier: Programming Language :: Python :: 3
Classifier: Programming Language :: Python :: 3.6
Classifier: Programming Language :: Python :: 3.7
Classifier: Programming Language :: Python :: 3.8
Classifier: Programming Language :: Python :: 3.9
Classifier: Operating System :: OS Independent
Requires-Python: >=3.6
License-File: LICENSE.txt
Requires-Dist: setuptools
Requires-Dist: aiohttp
Requires-Dist: tqdm
Requires-Dist: asyncio
